{"municipalities": [{"name": "المكناسي.xlsx", "projects": []}, {"name": "منزل بوزيان.xlsx", "projects": [{"name": "التنوير العمومي", "field": "بنية أساسية", "cost": 0.0, "type": "بلدي صرف", "planned cost": 64163.0, "description": ""}, {"name": "الطرقات و الارصفة", "field": "بنية أساسية", "cost": 0.0, "type": "بلدي صرف", "planned cost": 250000.0, "description": ""}, {"name": "تعهد و صيانة البنية الاساسية", "field": "بنية أساسية", "cost": 0.0, "type": "بلدي صرف", "planned cost": 60000.0, "description": ""}, {"name": "تجميل المدينة", "field": "تهيئة وتهذيب", "cost": 0.0, "type": "بلدي صرف", "planned cost": 120000.0, "description": ""}, {"name": "مأوى للسيارات", "field": "تهيئة وتهذيب", "cost": 0.0, "type": "بلدي صرف", "planned cost": 30000.0, "description": ""}, {"name": "اقتناء معدات", "field": "اقتناء معدات", "cost": 0.0, "type": "بلدي صرف", "planned cost": 120000.0, "description": ""}, {"name": "اقتناء معدات اعلامية", "field": "اقتناء معدات", "cost": 0.0, "type": "بلدي صرف", "planned cost": 29512.0, "description": ""}, {"name": "المستودع البلدي", "field": "تهيئة وتهذيب", "cost": 0.0, "type": "بلدي صرف", "planned cost": 50000.0, "description": ""}, {"name": "بناءات ادارية", "field": "بناءات إدارية", "cost": 0.0, "type": "بلدي صرف", "planned cost": 50000.0, "description": ""}, {"name": "قصر البلدية", "field": "بناءات إدارية", "cost": 0.0, "type": "بلدي صرف", "planned cost": 40000.0, "description": ""}, {"name": "دراسات", "field": "دراسات", "cost": 0.0, "type": "بلدي صرف", "planned cost": 20001.0, "description": ""}, {"name": "ملعب بلدي", "field": "تهيئة وتهذيب", "cost": 0.0, "type": "مشترك", "planned cost": 50000.0, "description": ""}, {"name": "تهذيب حي القصر الاحمر", "field": "تهيئة وتهذيب", "cost": 0.0, "type": "وطني", "planned cost": 500000.0, "description": ""}, {"name": "تهذيب حي الحسين بوزيان", "field": "تهيئة وتهذيب", "cost": 0.0, "type": "وطني", "planned cost": 614540.0, "description": ""}, {"name": "سوق الدواب", "field": "تهيئة وتهذيب", "cost": 0.0, "type": "وطني", "planned cost": 350000.0, "description": ""}]}, {"name": "بئر الحفي.xlsx", "projects": [{"name": "الطرقات و الارصفة", "field": "بنية أساسية", "cost": 0.0, "type": "بلدي صرف", "planned cost": 570000.0, "description": ""}, {"name": "التطهير و تصريف مياه الامطار", "field": "بنية أساسية", "cost": 0.0, "type": "بلدي صرف", "planned cost": 20000.0, "description": ""}, {"name": "التنوير العمومي", "field": "بنية أساسية", "cost": 0.0, "type": "بلدي صرف", "planned cost": 133649.0, "description": ""}, {"name": "تعهد و صيانة البنية الاساسية", "field": "بنية أساسية", "cost": 0.0, "type": "بلدي صرف", "planned cost": 80000.0, "description": ""}, {"name": "تجميل المدينة", "field": "تهيئة وتهذيب", "cost": 0.0, "type": "بلدي صرف", "planned cost": 110000.0, "description": ""}, {"name": "اقتناء معدات", "field": "اقتناء معدات", "cost": 0.0, "type": "بلدي صرف", "planned cost": 80000.0, "description": ""}, {"name": "اقتناء معدات اعلامية", "field": "اقتناء معدات", "cost": 0.0, "type": "بلدي صرف", "planned cost": 5018.0, "description": ""}, {"name": "تعهد و صيانة المنشأت البلدية", "field": "تهيئة وتهذيب", "cost": 0.0, "type": "بلدي صرف", "planned cost": 0.0, "description": ""}, {"name": "دراسات", "field": "دراسات", "cost": 0.0, "type": "بلدي صرف", "planned cost": 17500.0, "description": ""}, {"name": "الملعب البلدي", "field": "تهيئة وتهذيب", "cost": 0.0, "type": "مشترك", "planned cost": 200000.0, "description": ""}, {"name": "سوق الدواب", "field": "تهيئة وتهذيب", "cost": 0.0, "type": "وطني", "planned cost": 290000.0, "description": ""}]}, {"name": "أولاد حفوز.xlsx", "projects": []}, {"name": "سيدي علي بن عون.xlsx", "projects": []}, {"name": "سيدي بوزيد.xlsx", "projects": [{"name": "أشغال التهيئة المختلفة", "field": "", "cost": 0.0, "type": "", "planned cost": 300000.0, "description": ""}, {"name": "اقتناء وسائل النقل", "field": "", "cost": 0.0, "type": "", "planned cost": 218057.211, "description": ""}, {"name": "بناء ادارة", "field": "", "cost": 0.0, "type": "", "planned cost": 0.0, "description": ""}, {"name": "الصيانة و التعهد", "field": "", "cost": 0.0, "type": "", "planned cost": 120000.0, "description": ""}]}, {"name": "الرقاب.xlsx", "projects": []}, {"name": "جلمة.xlsx", "projects": []}, {"name": "المزونة.xlsx", "projects": [{"name": "الطرقات و الارصفة ", "field": "بنية أساسية", "cost": 180000.0, "type": "بلدي صرف", "planned cost": 200000.0, "description": ""}, {"name": "التنوير العمومي", "field": "بنية أساسية", "cost": 4908.0, "type": "بلدي صرف", "planned cost": 34908.0, "description": ""}, {"name": "تعهد و صيانة البنية الاساسية ", "field": "بنية أساسية", "cost": 60000.0, "type": "بلدي صرف", "planned cost": 60000.0, "description": ""}, {"name": "تجميل المدينة ", "field": "تهيئة وتهذيب", "cost": 365.0, "type": "بلدي صرف", "planned cost": 20365.0, "description": ""}, {"name": "حي تجاري ", "field": "", "cost": 30000.0, "type": "بلدي صرف", "planned cost": 30000.0, "description": ""}, {"name": "اقتناء معدات ", "field": "اقتناء معدات", "cost": 2363.0, "type": "بلدي صرف", "planned cost": 44408.0, "description": ""}, {"name": "اقتناء معدات اعلامية ", "field": "اقتناء معدات", "cost": 27955.0, "type": "بلدي صرف", "planned cost": 30000.0, "description": ""}, {"name": "المستودع البلدي", "field": "بناءات إدارية", "cost": 50000.0, "type": "بلدي صرف", "planned cost": 50000.0, "description": ""}, {"name": "تعهد و صيانة المنشات البلدية ", "field": "بناءات إدارية", "cost": 20000.0, "type": "بلدي صرف", "planned cost": 20000.0, "description": ""}, {"name": "دراسات ", "field": "دراسات", "cost": 5704.0, "type": "بلدي صرف", "planned cost": 5704.0, "description": ""}, {"name": "ملعب بلدي", "field": "", "cost": 10000.0, "type": "مشترك", "planned cost": 100000.0, "description": ""}, {"name": "مركب الطفولة ", "field": "", "cost": 400000.0, "type": "مشترك", "planned cost": 400000.0, "description": ""}, {"name": "الامل 1 و 2 ", "field": "تهيئة وتهذيب", "cost": 0.0, "type": "وطني", "planned cost": 325159.0, "description": ""}, {"name": "الاستقلال ", "field": "تهيئة وتهذيب", "cost": "", "type": "وطني", "planned cost": 400000.0, "description": ""}, {"name": "سوق بلدي", "field": "بنية أساسية", "cost": "", "type": "وطني", "planned cost": 30000.0, "description": ""}]}, {"name": "السبالة.xlsx", "projects": [{"name": "الطرقات و الارصفة ", "field": "بنية أساسية", "cost": 100000.0, "type": "بلدي صرف", "planned cost": 300000.0, "description": ""}, {"name": "التنوير العمومي", "field": "بنية أساسية", "cost": 70000.0, "type": "بلدي صرف", "planned cost": 70000.0, "description": ""}, {"name": "تعهد و صيانة البنية الاساسية ", "field": "بنية أساسية", "cost": 60000.0, "type": "بلدي صرف", "planned cost": 60000.0, "description": ""}, {"name": "تجميل المدينة ", "field": "تهيئة وتهذيب", "cost": 70000.0, "type": "بلدي صرف", "planned cost": 140000.0, "description": ""}, {"name": "اقتناء معدات ", "field": "اقتناء معدات", "cost": 17516.0, "type": "بلدي صرف", "planned cost": 107516.0, "description": ""}, {"name": "اقتناء معدات اعلامية ", "field": "اقتناء معدات", "cost": 387.0, "type": "بلدي صرف", "planned cost": 20387.0, "description": ""}, {"name": "تعهد و صيانة المنشات البلدية ", "field": "بنية أساسية", "cost": 30000.0, "type": "بلدي صرف", "planned cost": 30000.0, "description": ""}, {"name": "دراسات ", "field": "دراسات", "cost": 2964.0, "type": "بلدي صرف", "planned cost": 12964.0, "description": ""}, {"name": "ملعب بلدي ", "field": "تهيئة وتهذيب", "cost": 30000.0, "type": "مشترك", "planned cost": 30000.0, "description": ""}]}], "name": "سيدي بوزيد"}